[
  {
    "key": "datr",
    "value": "h3QAaG7-rnIRfsxJmJFGpOfj",
    "domain": "facebook.com",
    "path": "\/",
    "hostOnly": false,
    "creation": "2025-04-17T03:24:55.890Z",
    "lastAccessed": "2025-04-17T03:24:55.893Z"
  },
  {
    "key": "m_pixel_ratio",
    "value": "2.4000000953674316",
    "domain": "facebook.com",
    "path": "\/",
    "hostOnly": false,
    "creation": "2025-04-17T03:24:55.891Z",
    "lastAccessed": "2025-04-17T03:24:55.894Z"
  },
  {
    "key": "wd",
    "value": "492x880",
    "domain": "facebook.com",
    "path": "\/",
    "hostOnly": false,
    "creation": "2025-04-17T03:24:55.892Z",
    "lastAccessed": "2025-04-17T03:24:55.895Z"
  },
  {
    "key": "c_user",
    "value": "61575288690265",
    "domain": "facebook.com",
    "path": "\/",
    "hostOnly": false,
    "creation": "2025-04-17T03:24:55.893Z",
    "lastAccessed": "2025-04-17T03:24:55.896Z"
  },
  {
    "key": "fr",
    "value": "0DhmKZ26dASemNA2E.AWcZyH7wJLokj5GzAmOvek528E0ka8mw1ifn_On3Mt6jUwUzA_o.BoAHSH..AAA.0.0.BoAHSH.AWeHd6vdrZOJEda7S7yqcDufmnk",
    "domain": "facebook.com",
    "path": "\/",
    "hostOnly": false,
    "creation": "2025-04-17T03:24:55.894Z",
    "lastAccessed": "2025-04-17T03:24:55.897Z"
  },
  {
    "key": "xs",
    "value": "14:q1QJeUg4O26P9g:2:1744860295:-1:-1",
    "domain": "facebook.com",
    "path": "\/",
    "hostOnly": false,
    "creation": "2025-04-17T03:24:55.895Z",
    "lastAccessed": "2025-04-17T03:24:55.898Z"
  },
  {
    "key": "locale",
    "value": "en_US",
    "domain": "facebook.com",
    "path": "\/",
    "hostOnly": false,
    "creation": "2025-04-17T03:24:55.896Z",
    "lastAccessed": "2025-04-17T03:24:55.899Z"
  },
  {
    "key": "vpd",
    "value": "v1%3B880x492x2.4000000953674316",
    "domain": "facebook.com",
    "path": "\/",
    "hostOnly": false,
    "creation": "2025-04-17T03:24:55.897Z",
    "lastAccessed": "2025-04-17T03:24:55.900Z"
  }
]
